odoo8_addon_sale_sourced_by_line-8.0.1.1.0.99.dev24-py3.8-nspkg.pth
odoo_addons/sale_sourced_by_line/README.rst
odoo_addons/sale_sourced_by_line/__init__.py
odoo_addons/sale_sourced_by_line/__openerp__.py
odoo_addons/sale_sourced_by_line/i18n/ca.po
odoo_addons/sale_sourced_by_line/i18n/de.po
odoo_addons/sale_sourced_by_line/i18n/es.po
odoo_addons/sale_sourced_by_line/i18n/es_AR.po
odoo_addons/sale_sourced_by_line/i18n/es_ES.po
odoo_addons/sale_sourced_by_line/i18n/fi.po
odoo_addons/sale_sourced_by_line/i18n/fr.po
odoo_addons/sale_sourced_by_line/i18n/hr.po
odoo_addons/sale_sourced_by_line/i18n/hu.po
odoo_addons/sale_sourced_by_line/i18n/it.po
odoo_addons/sale_sourced_by_line/i18n/nl.po
odoo_addons/sale_sourced_by_line/i18n/nl_NL.po
odoo_addons/sale_sourced_by_line/i18n/pt_BR.po
odoo_addons/sale_sourced_by_line/i18n/ro.po
odoo_addons/sale_sourced_by_line/i18n/sale_sourced_by_line.pot
odoo_addons/sale_sourced_by_line/i18n/sk.po
odoo_addons/sale_sourced_by_line/i18n/sl.po
odoo_addons/sale_sourced_by_line/i18n/tr.po
odoo_addons/sale_sourced_by_line/i18n/tr_TR.po
odoo_addons/sale_sourced_by_line/i18n/zh_CN.po
odoo_addons/sale_sourced_by_line/migrations/8.0.1.1.0/openupgrade_analysis.txt
odoo_addons/sale_sourced_by_line/migrations/8.0.1.1.0/openupgrade_analysis_work.txt
odoo_addons/sale_sourced_by_line/migrations/8.0.1.1.0/post-migration.py
odoo_addons/sale_sourced_by_line/migrations/8.0.1.1.0/pre-migration.py
odoo_addons/sale_sourced_by_line/model/__init__.py
odoo_addons/sale_sourced_by_line/model/sale.py
odoo_addons/sale_sourced_by_line/model/stock.py
odoo_addons/sale_sourced_by_line/static/description/icon.png
odoo_addons/sale_sourced_by_line/test/sale_order_multi_source.yml
odoo_addons/sale_sourced_by_line/test/sale_order_not_sourced.yml
odoo_addons/sale_sourced_by_line/test/sale_order_source.yml
odoo_addons/sale_sourced_by_line/tests/__init__.py
odoo_addons/sale_sourced_by_line/tests/test_sale_is_delivered.py
odoo_addons/sale_sourced_by_line/view/sale_view.xml
odoo8_addon_sale_sourced_by_line-8.0.1.1.0.99.dev24.dist-info/METADATA
odoo8_addon_sale_sourced_by_line-8.0.1.1.0.99.dev24.dist-info/WHEEL
odoo8_addon_sale_sourced_by_line-8.0.1.1.0.99.dev24.dist-info/namespace_packages.txt
odoo8_addon_sale_sourced_by_line-8.0.1.1.0.99.dev24.dist-info/top_level.txt
odoo8_addon_sale_sourced_by_line-8.0.1.1.0.99.dev24.dist-info/RECORD
