Metadata-Version: 2.1
Name: odoo8-addon-sale-sourced-by-line
Version: 8.0.1.1.0.99.dev24
Summary: Multiple warehouse source locations for Sale order
Home-page: http://www.camptocamp.com
Author: Camptocamp,Odoo Community Association (OCA)
Author-email: support@odoo-community.org
License: AGPL-3
Platform: UNKNOWN
Classifier: Programming Language :: Python
Classifier: Framework :: Odoo
Classifier: Framework :: Odoo :: 8.0
Classifier: License :: OSI Approved :: GNU Affero General Public License v3
Requires-Python: ~=2.7
Requires-Dist: odoo8-addon-sale-procurement-group-by-line
Requires-Dist: odoo (<9.0a,>=8.0a)
